ascend_io_tools/__init__.py
ascend_io_tools/ingest/healthcare/hl7tojson.py
ascend_io_tools-1.0.0a1.dist-info/LICENSE
ascend_io_tools-1.0.0a1.dist-info/METADATA
ascend_io_tools-1.0.0a1.dist-info/WHEEL
ascend_io_tools-1.0.0a1.dist-info/RECORD
